aws_sqs_ext_client/__init__.py
aws_sqs_ext_client/constants.py
aws_sqs_ext_client/extended_messaging.py
aws_sqs_ext_client/session.py
aws_sqs_ext_client/models/__init__.py
aws_sqs_ext_client/models/payload_s3_pointer.py
aws_sqs_ext_client-0.0.7.dist-info/LICENSE
aws_sqs_ext_client-0.0.7.dist-info/METADATA
aws_sqs_ext_client-0.0.7.dist-info/WHEEL
aws_sqs_ext_client-0.0.7.dist-info/top_level.txt
aws_sqs_ext_client-0.0.7.dist-info/RECORD
