Metadata-Version: 2.1
Name: aws-sqs-ext-client
Version: 0.0.7
Summary: The Amazon SQS Extended Client Library for Python to send, receive, and delete large messages via S3
Home-page: https://github.com/archetype-digital/aws-sqs-extended
Author: Hiroshi Nakagoe
Author-email: hiroshi.nakakgoe@archetypedigital.us
License: UNKNOWN
Platform: UNKNOWN
Classifier: Development Status :: 4 - Beta
Classifier: Intended Audience :: Developers
Classifier: License :: OSI Approved :: MIT License
Classifier: Operating System :: OS Independent
Classifier: Programming Language :: Python :: 3.8
Classifier: Programming Language :: Python :: 3.9
Classifier: Programming Language :: Python :: 3 :: Only
Requires-Python: >=3.8
License-File: LICENSE
Requires-Dist: boto3 (~=1.26)
Provides-Extra: dev
Requires-Dist: flake8 ; extra == 'dev'
Requires-Dist: autopep8 ; extra == 'dev'
Provides-Extra: test
Requires-Dist: pytest ; extra == 'test'
Requires-Dist: pytest-cov ; extra == 'test'
Requires-Dist: moto[all] ; extra == 'test'
